MANIFEST.in
README.md
requirements.txt
setup.py
version.txt
apslite_agent/__init__.py
apslite_agent/certs.py
apslite_agent/config.py
apslite_agent/constants.py
apslite_agent/consumer.py
apslite_agent/exceptions.py
apslite_agent/main.py
apslite_agent/utils.py
apslite_agent.egg-info/PKG-INFO
apslite_agent.egg-info/SOURCES.txt
apslite_agent.egg-info/dependency_links.txt
apslite_agent.egg-info/entry_points.txt
apslite_agent.egg-info/requires.txt
apslite_agent.egg-info/top_level.txt
apslite_agent/tasks/__init__.py
apslite_agent/tasks/base.py
apslite_agent/tasks/create_session.py
apslite_agent/tasks/fake.py
apslite_agent/tasks/health_check.py
apslite_agent/tasks/openapi.py
apslite_agent/tasks/self_upgrade.py