Metadata-Version: 1.0
Name: apslite-agent
Version: 1.2.11
Summary: UNKNOWN
Home-page: http://aps.odin.com
Author: APS Lite team
Author-email: aps@odin.com
License: UNKNOWN
Platform: UNKNOWN
